Unittest/__init__.py
Unittest/test_server.py
Unittest/test_utils_setUp.py
Unittest/test_utils_setUpClass.py
common/__init__.py
common/decorator.py
common/descriptor.py
common/meta.py
common/utils.py
common/variables.py
log/__init__.py
log/server_log_config.py
MyStudyChat_server-1.0.1.dist-info/METADATA
MyStudyChat_server-1.0.1.dist-info/WHEEL
MyStudyChat_server-1.0.1.dist-info/top_level.txt
MyStudyChat_server-1.0.1.dist-info/RECORD
